.gitignore
.gitlab-ci.yml
CHANGELOG.rst
CONTRIBUTING.rst
LICENSE.txt
README.rst
setup.py
test.py
version.py
PICOS.egg-info/PKG-INFO
PICOS.egg-info/SOURCES.txt
PICOS.egg-info/dependency_links.txt
PICOS.egg-info/requires.txt
PICOS.egg-info/top_level.txt
ci/aur_install.sh
conda/.gitignore
conda/build.sh
conda/conda_build_config.yaml
conda/meta.yaml
conda/release.sh
doc/.gitignore
doc/Makefile
doc/api.rst
doc/badges.rst
doc/changelog.rst
doc/cheatsheet.rst
doc/complex.rst
doc/conf.py
doc/constraints.rst
doc/contributing.rst
doc/duals.rst
doc/examples.rst
doc/favicon.ico
doc/graphs.rst
doc/index.rst
doc/introduction.rst
doc/logo_text.png
doc/make.bat
doc/notes.rst
doc/numscipy.rst
doc/optdes.rst
doc/picos_trans.png
doc/picos_white.png
doc/qis.rst
doc/qrep.rst
doc/quick.rst
doc/slicing.rst
doc/tolerances.rst
doc/tutorial.rst
doc/_templates/autoapi/module.rst
picos/.version
picos/__init__.py
picos/apidoc.py
picos/caching.py
picos/containers.py
picos/formatting.py
picos/glyphs.py
picos/legacy.py
picos/settings.py
picos/tools.py
picos/uncertain.py
picos/valuable.py
picos/constraints/__init__.py
picos/constraints/con_absolute.py
picos/constraints/con_affine.py
picos/constraints/con_detrootn.py
picos/constraints/con_dummy.py
picos/constraints/con_expcone.py
picos/constraints/con_extremum.py
picos/constraints/con_flow.py
picos/constraints/con_geomean.py
picos/constraints/con_kldiv.py
picos/constraints/con_lmi.py
picos/constraints/con_log.py
picos/constraints/con_logsumexp.py
picos/constraints/con_matnorm.py
picos/constraints/con_mtxgeomean.py
picos/constraints/con_oprelentr.py
picos/constraints/con_powtrace.py
picos/constraints/con_prodcone.py
picos/constraints/con_quadratic.py
picos/constraints/con_quantcondentr.py
picos/constraints/con_quantkeydist.py
picos/constraints/con_quantrelentr.py
picos/constraints/con_renyientr.py
picos/constraints/con_rsoc.py
picos/constraints/con_simplex.py
picos/constraints/con_soc.py
picos/constraints/con_sqnorm.py
picos/constraints/con_sumexp.py
picos/constraints/con_sumxtr.py
picos/constraints/con_vecnorm.py
picos/constraints/con_wsum.py
picos/constraints/constraint.py
