Metadata-Version: 2.4
Name: PICOS
Version: 2.6.2
Summary: A Python interface to conic optimization solvers.
Author: G. Sagnol, M. Stahlberg
Author-email: incoming+picos-api/picos@incoming.gitlab.com
Project-URL: Source, https://gitlab.com/picos-api/picos
Project-URL: Documentation, https://picos-api.gitlab.io/picos/
Keywords: conic optimization,convex optimization,robust optimization,semidefinite programming
Classifier: Topic :: Scientific/Engineering :: Mathematics
Classifier: License :: OSI Approved :: GNU General Public License v3 (GPLv3)
Classifier: Programming Language :: Python
Classifier: Operating System :: OS Independent
Classifier: Intended Audience :: Science/Research
Requires-Python: >=3.4
License-File: LICENSE.txt
Requires-Dist: cvxopt
Requires-Dist: numpy
Dynamic: author
Dynamic: author-email
Dynamic: classifier
Dynamic: description
Dynamic: description-content-type
Dynamic: keywords
Dynamic: license-file
Dynamic: project-url
Dynamic: requires-dist
Dynamic: requires-python
Dynamic: summary
